adis16448/__init__.py
adis16448/_adis16448.cpython-39-x86_64-linux-gnu.so
adis16448/_init_adis16448.py
adis16448/pkgcfg.py
adis16448/__pycache__/__init__.cpython-39.pyc
adis16448/__pycache__/_init_adis16448.cpython-39.pyc
adis16448/_adis16448/__init__.pyi
adis16448/include/adi/ADIS16448_IMU.h
adis16448/rpy-include/rpygen/frc__ADIS16448_IMU.hpp
adis16448/src/ADIS16448_IMU.cpp
adis16448/src/module.cpp
adis16470/__init__.py
adis16470/_adis16470.cpython-39-x86_64-linux-gnu.so
adis16470/_init_adis16470.py
adis16470/pkgcfg.py
adis16470/version.py
adis16470/__pycache__/__init__.cpython-39.pyc
adis16470/__pycache__/_init_adis16470.cpython-39.pyc
adis16470/_adis16470/__init__.pyi
adis16470/include/adi/ADIS16470_IMU.h
adis16470/rpy-include/rpygen/frc__ADIS16470_IMU.hpp
adis16470/src/ADIS16470_IMU.cpp
adis16470/src/module.cpp
robotpy_adi-2021.0.0.dist-info/LICENSE
robotpy_adi-2021.0.0.dist-info/METADATA
robotpy_adi-2021.0.0.dist-info/WHEEL
robotpy_adi-2021.0.0.dist-info/entry_points.txt
robotpy_adi-2021.0.0.dist-info/top_level.txt
robotpy_adi-2021.0.0.dist-info/RECORD
