Metadata-Version: 2.1
Name: robotpy-adi
Version: 2021.0.0
Summary: RobotPy wrappers for Analog Devices IMU
Home-page: https://github.com/robotpy-adi
Author: RobotPy Development Team
Author-email: robotpy@googlegroups.com
License: MIT
Platform: UNKNOWN
Requires-Python: >=3.6
Requires-Dist: wpilib (<2022.0.0,>=2021.1.2.0)
